drf_api_checker/__init__.py
drf_api_checker/apps.py
drf_api_checker/collector.py
drf_api_checker/exceptions.py
drf_api_checker/fs.py
drf_api_checker/pytest.py
drf_api_checker/recorder.py
drf_api_checker/unittest.py
drf_api_checker/utils.py
drf_api_checker-0.13.dist-info/LICENSE
drf_api_checker-0.13.dist-info/METADATA
drf_api_checker-0.13.dist-info/WHEEL
drf_api_checker-0.13.dist-info/RECORD
