Metadata-Version: 2.3
Name: drf-api-checker
Version: 0.13
Summary: 
License: MIT
Author: sax
Author-email: s.apostolico@gmail.com
Requires-Python: >=3.9,<4.0
Classifier: License :: OSI Approved :: MIT License
Classifier: Programming Language :: Python :: 3
Classifier: Programming Language :: Python :: 3.9
Classifier: Programming Language :: Python :: 3.10
Classifier: Programming Language :: Python :: 3.11
Classifier: Programming Language :: Python :: 3.12
Classifier: Programming Language :: Python :: 3.13
Requires-Dist: Django
Requires-Dist: djangorestframework
Requires-Dist: pytz
